mlpype/tensorflow/__init__.py
mlpype/tensorflow/data/__init__.py
mlpype/tensorflow/data/tensor_source.py
mlpype/tensorflow/model/__init__.py
mlpype/tensorflow/model/keras_pype_model.py
mlpype/tensorflow/model/mlp_keras.py
mlpype/tensorflow/model/mlp_pype_model.py
mlpype/tensorflow/pipeline/__init__.py
mlpype/tensorflow/pipeline/tensor_checker.py
mlpype_tensorflow-0.6.12.dist-info/METADATA
mlpype_tensorflow-0.6.12.dist-info/WHEEL
mlpype_tensorflow-0.6.12.dist-info/RECORD
